README.md
setup.cfg
setup.py
ftpknocker/__init__.py
ftpknocker/cli.py
ftpknocker/utils.py
ftpknocker.egg-info/PKG-INFO
ftpknocker.egg-info/SOURCES.txt
ftpknocker.egg-info/dependency_links.txt
ftpknocker.egg-info/entry_points.txt
ftpknocker.egg-info/requires.txt
ftpknocker.egg-info/top_level.txt
test/test_scan.py
test/test_target_parsing.py